pypeworks/__init__.py
pypeworks/connection.py
pypeworks/node.py
pypeworks/nodes.py
pypeworks/pipework.py
pypeworks/pipeworks.py
pypeworks/util.py
pypeworks/typing/__init__.py
pypeworks/typing/future.py
pypeworks/typing/legacy.py
pypeworks-0.3.1.dist-info/licenses/LICENSE
pypeworks-0.3.1.dist-info/METADATA
pypeworks-0.3.1.dist-info/WHEEL
pypeworks-0.3.1.dist-info/top_level.txt
pypeworks-0.3.1.dist-info/RECORD
