Metadata-Version: 2.4
Name: pypeworks
Version: 0.3.1
Summary: A lightweight framework for parallel data processing using directed acyclic graphs
Author: Rosaia B.V.
License: 
Project-URL: Repository, https://github.com/rosaia/pypeworks
Keywords: data engineering,dataflows,directed acylic graphs
Classifier: Development Status :: 4 - Beta
Classifier: License :: OSI Approved :: Apache Software License
Classifier: Programming Language :: Python :: 3
Classifier: Operating System :: OS Independent
Classifier: Topic :: Software Development :: Libraries
Requires-Python: >=3.10
License-File: LICENSE
Requires-Dist: typing-extensions>=4.14.0
Dynamic: license-file
